{"stat.chestOpened":28,"stat.pickup.minecraft.rotten_flesh":8,"stat.pickup.minecraft.pumpkin":4,"stat.walkOneCm":143005,"stat.drop.minecraft.pumpkin":1,"stat.useItem.minecraft.bread":2,"stat.pickup.minecraft.bone":9,"stat.trappedChestTriggered":4,"stat.drop.minecraft.rotten_flesh":1,"stat.leaveGame":1,"stat.damageTaken":740,"stat.furnaceInteraction":2,"stat.killEntity.WitherSkeleton":6,"stat.pickup.minecraft.written_book":1,"stat.pickup.minecraft.concrete_powder":8,"stat.useItem.minecraft.apple":3,"stat.breakItem.minecraft.wooden_axe":1,"stat.mobKills":13,"stat.noteblockTuned":1,"stat.talkedToVillager":3,"stat.useItem.minecraft.potion":3,"stat.drop.minecraft.written_book":2,"stat.useItem.minecraft.rotten_flesh":4,"stat.flyOneCm":170583,"stat.breakItem.minecraft.wooden_sword":3,"stat.deaths":3,"stat.drop":4,"stat.jump":637,"stat.playOneMinute":37065,"stat.pickup.minecraft.coal":3,"stat.fallOneCm":4124,"stat.climbOneCm":2116,"stat.entityKilledBy.Zombie":1,"stat.useItem.minecraft.wooden_sword":90,"stat.sneakTime":274,"stat.shulkerBoxOpened":32,"stat.damageDealt":3279,"stat.crouchOneCm":978,"stat.enderchestOpened":4,"stat.killEntity.Zombie":7,"stat.timeSinceDeath":18753,"stat.useItem.minecraft.written_book":4,"stat.useItem.minecraft.wooden_axe":15,"stat.sprintOneCm":191123,"stat.craftingTableInteraction":2}