{"stat.chestOpened":3,"stat.walkOneCm":98401,"stat.trappedChestTriggered":1,"stat.pickup.minecraft.potion":1,"stat.leaveGame":1,"stat.damageTaken":530,"stat.pickup.minecraft.written_book":3,"stat.tradedWithVillager":7,"stat.mobKills":1,"stat.talkedToVillager":5,"stat.useItem.minecraft.potion":1,"stat.drop.minecraft.written_book":2,"stat.flyOneCm":33182,"stat.deaths":2,"stat.drop":1,"stat.craftItem.minecraft.iron_nugget":11,"stat.jump":122,"stat.playOneMinute":21467,"stat.climbOneCm":978,"stat.fallOneCm":806,"stat.useItem.minecraft.wooden_sword":8,"stat.entityKilledBy.Zombie":1,"stat.sneakTime":11,"stat.shulkerBoxOpened":14,"stat.damageDealt":114,"stat.timeSinceDeath":3267,"stat.useItem.minecraft.written_book":3,"stat.sprintOneCm":88110}