{"stat.chestOpened":15,"stat.pickup.minecraft.rotten_flesh":11,"stat.pickup.minecraft.pumpkin":1,"stat.walkOneCm":163155,"stat.useItem.minecraft.bread":7,"stat.pickup.minecraft.bone":5,"stat.trappedChestTriggered":4,"stat.leaveGame":1,"stat.damageTaken":414,"stat.furnaceInteraction":1,"stat.killEntity.WitherSkeleton":1,"stat.dispenserInspected":1,"stat.tradedWithVillager":4,"stat.useItem.minecraft.apple":6,"stat.mobKills":6,"stat.noteblockTuned":1,"stat.talkedToVillager":27,"stat.useItem.minecraft.potion":3,"stat.entityKilledBy.WitherSkeleton":1,"stat.useItem.minecraft.rotten_flesh":2,"stat.flyOneCm":335202,"stat.breakItem.minecraft.wooden_sword":1,"stat.deaths":1,"stat.craftItem.minecraft.iron_nugget":4,"stat.jump":1303,"stat.swimOneCm":901,"stat.playOneMinute":72438,"stat.pickup.minecraft.coal":1,"stat.fallOneCm":7636,"stat.climbOneCm":860,"stat.useItem.minecraft.wooden_sword":30,"stat.sneakTime":255,"stat.shulkerBoxOpened":20,"stat.damageDealt":508,"stat.crouchOneCm":296,"stat.enderchestOpened":4,"stat.sleepInBed":1,"stat.timeSinceDeath":21716,"stat.useItem.minecraft.written_book":1,"stat.sprintOneCm":292142,"stat.craftingTableInteraction":1}